mirror_docs.py
mirror_docs-0.1.4.dist-info/licenses/LICENSE
mirror_docs-0.1.4.dist-info/METADATA
mirror_docs-0.1.4.dist-info/WHEEL
mirror_docs-0.1.4.dist-info/entry_points.txt
mirror_docs-0.1.4.dist-info/top_level.txt
mirror_docs-0.1.4.dist-info/RECORD
