Metadata-Version: 2.4
Name: mirror-docs
Version: 0.1.4
Summary: Mirrors HTML documentation to Markdown for AI integration
Author-email: Joe Still <joe@bioshazard.com>
License: MIT
Classifier: Development Status :: 4 - Beta
Classifier: Intended Audience :: Developers
Classifier: Topic :: Software Development :: Documentation
Classifier: License :: OSI Approved :: MIT License
Classifier: Programming Language :: Python :: 3
Classifier: Programming Language :: Python :: 3.10
Classifier: Programming Language :: Python :: 3.11
Classifier: Programming Language :: Python :: 3.12
Classifier: Programming Language :: Python :: 3.13
Classifier: Operating System :: OS Independent
Requires-Python: >=3.10
License-File: LICENSE
Requires-Dist: lxml[html-clean]>=5.3.2
Requires-Dist: markdownify>=1.1.0
Requires-Dist: readability-lxml>=0.8.1
Requires-Dist: beautifulsoup4>=4.12.0
Dynamic: license-file
